<?xml version="1.0" encoding="UTF-8"?>
<person>
    <id>bell-david-elliott</id>
    <persName>
        <surname>Bell</surname>
        <forename>David Elliott</forename>
        <altname>David Elliot Bell</altname>
    </persName>
    <birth>1919</birth>
    <death>2000</death>
    <career-type>non-career</career-type>
    <residence>
        <state-id>ma</state-id>
    </residence>
    <created-by>wicentowskijc</created-by>
    <created-date>2010-05-20</created-date>
    <last-modified-by>wicentowskijc</last-modified-by>
    <last-modified-date>2010-05-20</last-modified-date>
</person>