<?xml version="1.0" encoding="UTF-8"?>
<principal-position>
    <id>counselor</id>
    <class>principal</class>
    <category>under-secretary</category>
    <names>
        <singular>Counselor</singular>
        <plural>Counselors</plural>
    </names>
    <start>1912</start>
    <end>2005</end>
    <ongoing>false</ongoing>
    <description>
        <div>
            <p>The Secretary of State created the position of Counselor for the Department of State
                in 1909 as part of a general Department reorganization. In 1912, the position became
                a Presidential appointment (37 Stat. 372). Between 1913 and 1919, the Counselor
                served as the Department’s second-ranking officer, assuming the role previously
                exercised by the Assistant Secretary of State. In 1919., the newly-created position
                of Under Secretary of State subsumed the duties of the Counselor. An Act of
                Congress, May 18, 1937, re-established the position of Counselor of the Department
                of State (50 Stat. 169). Between 1961 and 1965, the Counselor also served as the
                Chairman of the Policy Planning Council. The Counselor, who currently under law
                holds rank equivalent to an Under Secretary of State (P.L. 98-164; 97 Stat. 1017),
                serves as an adviser to the Secretary of State. The Counselor’s specific
                responsibilities have varied over time. This list does not include a Counselor for
                the Department of State appointed by the Secretary of State in 1909. On April 30,
                1994 the title was changed to Under Secretary of State for Global Affairs.</p>
        </div>
    </description>
    <is-dirty>false</is-dirty>
    <principals>
        <principal>
            <id>coun-1912-ande</id>
            <person-id>anderson-chandler-parsons</person-id>
            <role-title-id>counselor</role-title-id>
            <appointed>
                <date>1912-08-23</date>
                <note/>
            </appointed>
            <started>
                <date/>
                <note/>
            </started>
            <ended>
                <date/>
                <note/>
            </ended>
            <note>Commissioned as Counselor for the Department of State. Had been serving since Dec
                16, 1910, under an appointment by the Secretary of State.</note>
            <created-by>wicentowskijc</created-by>
            <created-date>2010-05-20</created-date>
            <last-modified-by>wicentowskijc</last-modified-by>
            <last-modified-date>2010-05-20</last-modified-date>
        </principal>
        <principal>
            <id>coun-1913-moor</id>
            <person-id>moore-john-bassett</person-id>
            <role-title-id>counselor</role-title-id>
            <appointed>
                <date>1913-04-21</date>
                <note/>
            </appointed>
            <started>
                <date/>
                <note/>
            </started>
            <ended>
                <date/>
                <note/>
            </ended>
            <note>Commissioned as Counselor for the Department of State.</note>
            <created-by>wicentowskijc</created-by>
            <created-date>2010-05-20</created-date>
            <last-modified-by>wicentowskijc</last-modified-by>
            <last-modified-date>2010-05-20</last-modified-date>
        </principal>
        <principal>
            <id>coun-1914-lans</id>
            <person-id>lansing-robert</person-id>
            <role-title-id>counselor</role-title-id>
            <appointed>
                <date>1914-03-27</date>
                <note/>
            </appointed>
            <started>
                <date/>
                <note/>
            </started>
            <ended>
                <date/>
                <note/>
            </ended>
            <note>Commissioned as Counselor for the Department of State.</note>
            <created-by>wicentowskijc</created-by>
            <created-date>2010-05-20</created-date>
            <last-modified-by>wicentowskijc</last-modified-by>
            <last-modified-date>2010-05-20</last-modified-date>
        </principal>
        <principal>
            <id>coun-1915-polk</id>
            <person-id>polk-frank-lyon</person-id>
            <role-title-id>counselor</role-title-id>
            <appointed>
                <date>1915-08-30</date>
                <note/>
            </appointed>
            <started>
                <date/>
                <note/>
            </started>
            <ended>
                <date/>
                <note/>
            </ended>
            <note>Commissioned as Counselor for the Department of State. Commissioned during a
                recess of the Senate; recommissioned after confirmation on Dec 17, 1915.</note>
            <created-by>wicentowskijc</created-by>
            <created-date>2010-05-20</created-date>
            <last-modified-by>wicentowskijc</last-modified-by>
            <last-modified-date>2010-05-20</last-modified-date>
        </principal>
        <principal>
            <id>coun-1937-moor</id>
            <person-id>moore-robert-walton</person-id>
            <role-title-id>counselor</role-title-id>
            <appointed>
                <date>1937-05-20</date>
                <note/>
            </appointed>
            <started>
                <date/>
                <note/>
            </started>
            <ended>
                <date/>
                <note/>
            </ended>
            <note/>
            <created-by>wicentowskijc</created-by>
            <created-date>2010-05-20</created-date>
            <last-modified-by>wicentowskijc</last-modified-by>
            <last-modified-date>2010-05-20</last-modified-date>
        </principal>
        <principal>
            <id>coun-1945-cohe</id>
            <person-id>cohen-benjamin-victor</person-id>
            <role-title-id>counselor</role-title-id>
            <appointed>
                <date>1945-09-14</date>
                <note/>
            </appointed>
            <started>
                <date/>
                <note/>
            </started>
            <ended>
                <date/>
                <note/>
            </ended>
            <note/>
            <created-by>wicentowskijc</created-by>
            <created-date>2010-05-20</created-date>
            <last-modified-by>wicentowskijc</last-modified-by>
            <last-modified-date>2010-05-20</last-modified-date>
        </principal>
        <principal>
            <id>coun-1947-bohl</id>
            <person-id>bohlen-charles-eustis</person-id>
            <role-title-id>counselor</role-title-id>
            <appointed>
                <date>1947-07-24</date>
                <note/>
            </appointed>
            <started>
                <date/>
                <note/>
            </started>
            <ended>
                <date/>
                <note/>
            </ended>
            <note/>
            <created-by>wicentowskijc</created-by>
            <created-date>2010-05-20</created-date>
            <last-modified-by>wicentowskijc</last-modified-by>
            <last-modified-date>2010-05-20</last-modified-date>
        </principal>
        <principal>
            <id>coun-1949-kenn</id>
            <person-id>kennan-george-frost</person-id>
            <role-title-id>counselor</role-title-id>
            <appointed>
                <date>1949-06-24</date>
                <note/>
            </appointed>
            <started>
                <date/>
                <note/>
            </started>
            <ended>
                <date/>
                <note/>
            </ended>
            <note/>
            <created-by>wicentowskijc</created-by>
            <created-date>2010-05-20</created-date>
            <last-modified-by>wicentowskijc</last-modified-by>
            <last-modified-date>2010-05-20</last-modified-date>
        </principal>
        <principal>
            <id>coun-1951-bohl</id>
            <person-id>bohlen-charles-eustis</person-id>
            <role-title-id>counselor</role-title-id>
            <appointed>
                <date>1951-03-13</date>
                <note/>
            </appointed>
            <started>
                <date/>
                <note/>
            </started>
            <ended>
                <date/>
                <note/>
            </ended>
            <note/>
            <created-by>wicentowskijc</created-by>
            <created-date>2010-05-20</created-date>
            <last-modified-by>wicentowskijc</last-modified-by>
            <last-modified-date>2010-05-20</last-modified-date>
        </principal>
        <principal>
            <id>coun-1953-maca</id>
            <person-id>macarthur-douglas</person-id>
            <role-title-id>counselor</role-title-id>
            <appointed>
                <date>1953-03-11</date>
                <note/>
            </appointed>
            <started>
                <date/>
                <note/>
            </started>
            <ended>
                <date/>
                <note/>
            </ended>
            <note/>
            <created-by>wicentowskijc</created-by>
            <created-date>2010-05-20</created-date>
            <last-modified-by>wicentowskijc</last-modified-by>
            <last-modified-date>2010-05-20</last-modified-date>
        </principal>
        <principal>
            <id>coun-1957-rein</id>
            <person-id>reinhardt-george-frederick</person-id>
            <role-title-id>counselor</role-title-id>
            <appointed>
                <date>1957-03-14</date>
                <note/>
            </appointed>
            <started>
                <date/>
                <note/>
            </started>
            <ended>
                <date/>
                <note/>
            </ended>
            <note/>
            <created-by>wicentowskijc</created-by>
            <created-date>2010-05-20</created-date>
            <last-modified-by>wicentowskijc</last-modified-by>
            <last-modified-date>2010-05-20</last-modified-date>
        </principal>
        <principal>
            <id>coun-1960-achi</id>
            <person-id>achilles-theodore-carter</person-id>
            <role-title-id>counselor</role-title-id>
            <appointed>
                <date>1960-03-18</date>
                <note/>
            </appointed>
            <started>
                <date/>
                <note/>
            </started>
            <ended>
                <date/>
                <note/>
            </ended>
            <note/>
            <created-by>wicentowskijc</created-by>
            <created-date>2010-05-20</created-date>
            <last-modified-by>wicentowskijc</last-modified-by>
            <last-modified-date>2010-05-20</last-modified-date>
        </principal>
        <principal>
            <id>coun-1961-mcgh</id>
            <person-id>mcghee-george-crews</person-id>
            <role-title-id>counselor</role-title-id>
            <appointed>
                <date>1961-02-13</date>
                <note/>
            </appointed>
            <started>
                <date/>
                <note/>
            </started>
            <ended>
                <date/>
                <note/>
            </ended>
            <note/>
            <created-by>wicentowskijc</created-by>
            <created-date>2010-05-20</created-date>
            <last-modified-by>marrsaw</last-modified-by>
            <last-modified-date>2013-04-15</last-modified-date>
        </principal>
        <principal>
            <id>coun-1961-rost</id>
            <person-id>rostow-walt-whitman</person-id>
            <role-title-id>counselor</role-title-id>
            <appointed>
                <date>1961-11-29</date>
                <note/>
            </appointed>
            <started>
                <date/>
                <note/>
            </started>
            <ended>
                <date/>
                <note/>
            </ended>
            <note>Commissioned during a recess of the Senate; recommissioned after confirmation on
                Mar 5, 1962.</note>
            <created-by>wicentowskijc</created-by>
            <created-date>2010-05-20</created-date>
            <last-modified-by>wicentowskijc</last-modified-by>
            <last-modified-date>2010-05-20</last-modified-date>
        </principal>
        <principal>
            <id>coun-1966-bowi</id>
            <person-id>bowie-robert-richardson</person-id>
            <role-title-id>counselor</role-title-id>
            <appointed>
                <date>1966-09-21</date>
                <note/>
            </appointed>
            <started>
                <date/>
                <note/>
            </started>
            <ended>
                <date/>
                <note/>
            </ended>
            <note/>
            <created-by>wicentowskijc</created-by>
            <created-date>2010-05-20</created-date>
            <last-modified-by>wicentowskijc</last-modified-by>
            <last-modified-date>2010-05-20</last-modified-date>
        </principal>
        <principal>
            <id>coun-1969-pede</id>
            <person-id>pedersen-richard-foote</person-id>
            <role-title-id>counselor</role-title-id>
            <appointed>
                <date>1969-01-23</date>
                <note/>
            </appointed>
            <started>
                <date/>
                <note/>
            </started>
            <ended>
                <date/>
                <note/>
            </ended>
            <note/>
            <created-by>wicentowskijc</created-by>
            <created-date>2010-05-20</created-date>
            <last-modified-by>wicentowskijc</last-modified-by>
            <last-modified-date>2010-05-20</last-modified-date>
        </principal>
        <principal>
            <id>coun-1973-sonn</id>
            <person-id>sonnenfeldt-helmut</person-id>
            <role-title-id>counselor</role-title-id>
            <appointed>
                <date>1973-12-19</date>
                <note/>
            </appointed>
            <started>
                <date/>
                <note/>
            </started>
            <ended>
                <date/>
                <note/>
            </ended>
            <note/>
            <created-by>wicentowskijc</created-by>
            <created-date>2010-05-20</created-date>
            <last-modified-by>marrsaw</last-modified-by>
            <last-modified-date>2013-04-30</last-modified-date>
        </principal>
        <principal>
            <id>coun-1977-nime</id>
            <person-id>nimetz-matthew</person-id>
            <role-title-id>counselor</role-title-id>
            <appointed>
                <date>1977-03-30</date>
                <note/>
            </appointed>
            <started>
                <date/>
                <note/>
            </started>
            <ended>
                <date/>
                <note/>
            </ended>
            <note/>
            <created-by>wicentowskijc</created-by>
            <created-date>2010-05-20</created-date>
            <last-modified-by>wicentowskijc</last-modified-by>
            <last-modified-date>2010-05-20</last-modified-date>
        </principal>
        <principal>
            <id>coun-1980-ridg</id>
            <person-id>ridgway-rozanne-lejeanne</person-id>
            <role-title-id>counselor</role-title-id>
            <appointed>
                <date>1980-03-18</date>
                <note/>
            </appointed>
            <started>
                <date/>
                <note/>
            </started>
            <ended>
                <date/>
                <note/>
            </ended>
            <note/>
            <created-by>wicentowskijc</created-by>
            <created-date>2010-05-20</created-date>
            <last-modified-by>wicentowskijc</last-modified-by>
            <last-modified-date>2010-05-20</last-modified-date>
        </principal>
        <principal>
            <id>coun-1981-mcfa</id>
            <person-id>mcfarlane-robert-carl</person-id>
            <role-title-id>counselor</role-title-id>
            <appointed>
                <date>1981-02-27</date>
                <note/>
            </appointed>
            <started>
                <date/>
                <note/>
            </started>
            <ended>
                <date/>
                <note/>
            </ended>
            <note/>
            <created-by>wicentowskijc</created-by>
            <created-date>2010-05-20</created-date>
            <last-modified-by>wicentowskijc</last-modified-by>
            <last-modified-date>2010-05-20</last-modified-date>
        </principal>
        <principal>
            <id>coun-1982-buck</id>
            <person-id>buckley-james-lane</person-id>
            <role-title-id>counselor</role-title-id>
            <appointed>
                <date>1982-08-20</date>
                <note/>
            </appointed>
            <started>
                <date/>
                <note/>
            </started>
            <ended>
                <date/>
                <note/>
            </ended>
            <note/>
            <created-by>wicentowskijc</created-by>
            <created-date>2010-05-20</created-date>
            <last-modified-by>wicentowskijc</last-modified-by>
            <last-modified-date>2010-05-20</last-modified-date>
        </principal>
        <principal>
            <id>coun-1983-derw</id>
            <person-id>derwinski-edward-j</person-id>
            <role-title-id>counselor</role-title-id>
            <appointed>
                <date>1983-03-18</date>
                <note/>
            </appointed>
            <started>
                <date/>
                <note/>
            </started>
            <ended>
                <date/>
                <note/>
            </ended>
            <note/>
            <created-by>wicentowskijc</created-by>
            <created-date>2010-05-20</created-date>
            <last-modified-by>admin</last-modified-by>
            <last-modified-date>2012-09-24</last-modified-date>
        </principal>
        <principal>
            <id>coun-1987-kamp</id>
            <person-id>kampelman-max-m</person-id>
            <role-title-id>counselor</role-title-id>
            <appointed>
                <date>1987-07-02</date>
                <note/>
            </appointed>
            <started>
                <date/>
                <note/>
            </started>
            <ended>
                <date/>
                <note/>
            </ended>
            <note/>
            <created-by>wicentowskijc</created-by>
            <created-date>2010-05-20</created-date>
            <last-modified-by>marrsaw</last-modified-by>
            <last-modified-date>2013-04-11</last-modified-date>
        </principal>
        <principal>
            <id>coun-1989-zoel</id>
            <person-id>zoellick-robert-b</person-id>
            <role-title-id>counselor</role-title-id>
            <appointed>
                <date>1989-03-02</date>
                <note/>
            </appointed>
            <started>
                <date/>
                <note/>
            </started>
            <ended>
                <date/>
                <note/>
            </ended>
            <note>Served concurrently as Under Secretary of State for Economic and Agricultural
                Affairs from May 9, 1991.</note>
            <created-by>wicentowskijc</created-by>
            <created-date>2010-05-20</created-date>
            <last-modified-by>wicentowskijc</last-modified-by>
            <last-modified-date>2010-05-20</last-modified-date>
        </principal>
        <principal>
            <id>coun-1993-wirt</id>
            <person-id>wirth-timothy-endicott</person-id>
            <role-title-id>counselor</role-title-id>
            <appointed>
                <date>1993-04-22</date>
                <note/>
            </appointed>
            <started>
                <date/>
                <note/>
            </started>
            <ended>
                <date/>
                <note/>
            </ended>
            <note>Became Under Secretary of State for Global Affairs, Apr 30, 1994.</note>
            <created-by>wicentowskijc</created-by>
            <created-date>2010-05-20</created-date>
            <last-modified-by>wicentowskijc</last-modified-by>
            <last-modified-date>2010-05-20</last-modified-date>
        </principal>
        <principal>
            <id>coun-1997-sher</id>
            <person-id>sherman-wendy-r</person-id>
            <role-title-id>counselor</role-title-id>
            <appointed>
                <date>1997-08-01</date>
                <note/>
            </appointed>
            <started>
                <date/>
                <note/>
            </started>
            <ended>
                <date/>
                <note/>
            </ended>
            <note/>
            <created-by>wicentowskijc</created-by>
            <created-date>2010-05-20</created-date>
            <last-modified-by>marrsaw</last-modified-by>
            <last-modified-date>2013-12-12</last-modified-date>
        </principal>
        <principal>
            <id>coun-2005-zeli</id>
            <person-id>zelikow-philip-d</person-id>
            <role-title-id>counselor</role-title-id>
            <appointed>
                <date/>
                <note/>
            </appointed>
            <started>
                <date/>
                <note/>
            </started>
            <ended>
                <date/>
                <note/>
            </ended>
            <note/>
            <created-by>wicentowskijc</created-by>
            <created-date>2010-05-20</created-date>
            <last-modified-by>wicentowskijc</last-modified-by>
            <last-modified-date>2010-05-20</last-modified-date>
        </principal>
        <principal>
            <id>coun-2007-cohe</id>
            <person-id>cohen-eliot-asher</person-id>
            <role-title-id>counselor</role-title-id>
            <appointed>
                <date/>
                <note/>
            </appointed>
            <started>
                <date/>
                <note/>
            </started>
            <ended>
                <date/>
                <note/>
            </ended>
            <note/>
            <created-by>wicentowskijc</created-by>
            <created-date>2010-05-20</created-date>
            <last-modified-by>marrsaw</last-modified-by>
            <last-modified-date>2016-12-02</last-modified-date>
        </principal>
        <principal>
            <id>coun-2009-mill</id>
            <person-id>mills-cheryl</person-id>
            <role-title-id>counselor</role-title-id>
            <appointed>
                <date>2009-05-24</date>
                <note/>
            </appointed>
            <started>
                <date/>
                <note/>
            </started>
            <ended>
                <date/>
                <note/>
            </ended>
            <note/>
            <created-by>wicentowskijc</created-by>
            <created-date>2010-11-05</created-date>
            <last-modified-by>marrsaw</last-modified-by>
            <last-modified-date>2014-07-15</last-modified-date>
        </principal>
        <principal>
            <id>coun-2013-shan</id>
            <person-id>shannon-thomas-alfred</person-id>
            <role-title-id>counselor</role-title-id>
            <appointed>
                <date>2013-12-24</date>
                <note/>
            </appointed>
            <started>
                <date/>
                <note/>
            </started>
            <ended>
                <date/>
                <note/>
            </ended>
            <note/>
            <created-by>wicentowskijc</created-by>
            <created-date>2010-11-05</created-date>
            <last-modified-by>marrsaw</last-modified-by>
            <last-modified-date>2016-08-20</last-modified-date>
        </principal>
        <principal>
            <id>coun-2016-kenn</id>
            <person-id>kenney-kristie-ann</person-id>
            <role-title-id>counselor</role-title-id>
            <appointed>
                <date/>
                <note/>
            </appointed>
            <started>
                <date/>
                <note/>
            </started>
            <ended>
                <date/>
                <note/>
            </ended>
            <note/>
            <created-by>marrsaw</created-by>
            <created-date>2016-08-25</created-date>
            <last-modified-by>bottsjd</last-modified-by>
            <last-modified-date>2019-02-06</last-modified-date>
        </principal>
        <principal>
            <id>coun-2017-beam</id>
            <person-id>beams-mary-elizabeth</person-id>
            <role-title-id>counselor</role-title-id>
            <appointed>
                <date>2017-08-17</date>
                <note/>
            </appointed>
            <started>
                <date/>
                <note/>
            </started>
            <ended>
                <date/>
                <note/>
            </ended>
            <note/>
            <created-by>bottsjd</created-by>
            <created-date>2019-02-06</created-date>
            <last-modified-by>bottsjd</last-modified-by>
            <last-modified-date>2019-03-21</last-modified-date>
        </principal>
        <principal>
            <id>coun-2018-brec</id>
            <person-id>brechbuhl-t-ulrich</person-id>
            <role-title-id>counselor</role-title-id>
            <appointed>
                <date>2018-05-01</date>
                <note/>
            </appointed>
            <started>
                <date/>
                <note/>
            </started>
            <ended>
                <date/>
                <note/>
            </ended>
            <note/>
            <created-by>bottsjd</created-by>
            <created-date>2019-03-20</created-date>
            <last-modified-by>bottsjd</last-modified-by>
            <last-modified-date>2021-02-18</last-modified-date>
        </principal>
    </principals>
    <other-appointees/>
</principal-position>