<?xml version="1.0" encoding="UTF-8"?>
<principal-position>
    <id>executive-secretary</id>
    <class>principal</class>
    <category>assistant-secretary-or-equiv</category>
    <names>
        <singular>Executive Secretary</singular>
        <plural>Executive Secretaries</plural>
    </names>
    <start>1961</start>
    <end>2005</end>
    <ongoing>false</ongoing>
    <description>
        <div>
            <p>In 1961, the Department of State conferred on the Director of the Executive
                Secretariat the title of Special Assistant to the Secretary of State and Executive
                Secretary, along with rank equivalent to an Assistant Secretary of State. Since
                then, the Secretary of State has designated all incumbents. The Department
                established the Executive Secretariat in Mar 1947 to regulate the flow of
                information within the highest levels of the Department. Its functions have included
                such various assignments as Protocol (prior to 1955), management of the Department’s
                Operation Center (since 1962) and preparation of briefing papers about the
                Department during the transitions between Presidential administrations.</p>
        </div>
    </description>
    <is-dirty>false</is-dirty>
    <principals>
        <principal>
            <id>secr-1961-batt</id>
            <person-id>battle-lucius-durham</person-id>
            <role-title-id>executive-secretary</role-title-id>
            <appointed>
                <date>1961-03-16</date>
                <note/>
            </appointed>
            <started>
                <date/>
                <note/>
            </started>
            <ended>
                <date>1962-05-02</date>
                <note/>
            </ended>
            <note/>
            <created-by>wicentowskijc</created-by>
            <created-date>2010-05-20</created-date>
            <last-modified-by>marrsaw</last-modified-by>
            <last-modified-date>2013-03-18</last-modified-date>
        </principal>
        <principal>
            <id>secr-1962-brub</id>
            <person-id>brubeck-william-h</person-id>
            <role-title-id>executive-secretary</role-title-id>
            <appointed>
                <date>1962-05-14</date>
                <note/>
            </appointed>
            <started>
                <date/>
                <note/>
            </started>
            <ended>
                <date>1963-07-20</date>
                <note/>
            </ended>
            <note/>
            <created-by>wicentowskijc</created-by>
            <created-date>2010-05-20</created-date>
            <last-modified-by>wicentowskijc</last-modified-by>
            <last-modified-date>2010-05-20</last-modified-date>
        </principal>
        <principal>
            <id>secr-1963-read</id>
            <person-id>read-benjamin-huger</person-id>
            <role-title-id>executive-secretary</role-title-id>
            <appointed>
                <date>1963-08-04</date>
                <note/>
            </appointed>
            <started>
                <date/>
                <note/>
            </started>
            <ended>
                <date>1969-02-14</date>
                <note/>
            </ended>
            <note/>
            <created-by>wicentowskijc</created-by>
            <created-date>2010-05-20</created-date>
            <last-modified-by>wicentowskijc</last-modified-by>
            <last-modified-date>2010-05-20</last-modified-date>
        </principal>
        <principal>
            <id>secr-1969-elio</id>
            <person-id>eliot-theodore-lyman</person-id>
            <role-title-id>executive-secretary</role-title-id>
            <appointed>
                <date>1969-08-10</date>
                <note/>
            </appointed>
            <started>
                <date/>
                <note/>
            </started>
            <ended>
                <date>1973-09-26</date>
                <note/>
            </ended>
            <note/>
            <created-by>wicentowskijc</created-by>
            <created-date>2010-05-20</created-date>
            <last-modified-by>wicentowskijc</last-modified-by>
            <last-modified-date>2010-05-20</last-modified-date>
        </principal>
        <principal>
            <id>secr-1973-pick</id>
            <person-id>pickering-thomas-reeve</person-id>
            <role-title-id>executive-secretary</role-title-id>
            <appointed>
                <date>1973-07-30</date>
                <note/>
            </appointed>
            <started>
                <date/>
                <note/>
            </started>
            <ended>
                <date>1974-01-31</date>
                <note/>
            </ended>
            <note/>
            <created-by>wicentowskijc</created-by>
            <created-date>2010-05-20</created-date>
            <last-modified-by>wicentowskijc</last-modified-by>
            <last-modified-date>2011-05-26</last-modified-date>
        </principal>
        <principal>
            <id>secr-1974-spri</id>
            <person-id>springsteen-george-stoney</person-id>
            <role-title-id>executive-secretary</role-title-id>
            <appointed>
                <date>1974-01-31</date>
                <note/>
            </appointed>
            <started>
                <date/>
                <note/>
            </started>
            <ended>
                <date>1976-07-14</date>
                <note/>
            </ended>
            <note/>
            <created-by>wicentowskijc</created-by>
            <created-date>2010-05-20</created-date>
            <last-modified-by>wicentowskijc</last-modified-by>
            <last-modified-date>2010-05-20</last-modified-date>
        </principal>
        <principal>
            <id>secr-1976-borg</id>
            <person-id>borg-c-arthur</person-id>
            <role-title-id>executive-secretary</role-title-id>
            <appointed>
                <date>1976-07-12</date>
                <note/>
            </appointed>
            <started>
                <date/>
                <note/>
            </started>
            <ended>
                <date>1977-04-15</date>
                <note/>
            </ended>
            <note/>
            <created-by>wicentowskijc</created-by>
            <created-date>2010-05-20</created-date>
            <last-modified-by>marrsaw</last-modified-by>
            <last-modified-date>2013-03-21</last-modified-date>
        </principal>
        <principal>
            <id>secr-1977-tarn</id>
            <person-id>tarnoff-peter</person-id>
            <role-title-id>executive-secretary</role-title-id>
            <appointed>
                <date>1977-04-04</date>
                <note/>
            </appointed>
            <started>
                <date/>
                <note/>
            </started>
            <ended>
                <date>1981-02-08</date>
                <note/>
            </ended>
            <note/>
            <created-by>wicentowskijc</created-by>
            <created-date>2010-05-20</created-date>
            <last-modified-by>wicentowskijc</last-modified-by>
            <last-modified-date>2010-05-20</last-modified-date>
        </principal>
        <principal>
            <id>secr-1981-brem</id>
            <person-id>bremer-l-paul</person-id>
            <role-title-id>executive-secretary</role-title-id>
            <appointed>
                <date>1981-02-02</date>
                <note/>
            </appointed>
            <started>
                <date/>
                <note/>
            </started>
            <ended>
                <date>1983-03-27</date>
                <note/>
            </ended>
            <note/>
            <created-by>wicentowskijc</created-by>
            <created-date>2010-05-20</created-date>
            <last-modified-by>wicentowskijc</last-modified-by>
            <last-modified-date>2010-05-20</last-modified-date>
        </principal>
        <principal>
            <id>secr-1983-hill</id>
            <person-id>hill-m-charles</person-id>
            <role-title-id>executive-secretary</role-title-id>
            <appointed>
                <date>1983-03-28</date>
                <note/>
            </appointed>
            <started>
                <date/>
                <note/>
            </started>
            <ended>
                <date>1985-01-01</date>
                <note/>
            </ended>
            <note/>
            <created-by>wicentowskijc</created-by>
            <created-date>2010-05-20</created-date>
            <last-modified-by>wicentowskijc</last-modified-by>
            <last-modified-date>2010-05-20</last-modified-date>
        </principal>
        <principal>
            <id>secr-1985-plat</id>
            <person-id>platt-nicholas</person-id>
            <role-title-id>executive-secretary</role-title-id>
            <appointed>
                <date>1985-01-07</date>
                <note/>
            </appointed>
            <started>
                <date/>
                <note/>
            </started>
            <ended>
                <date>1987-02-13</date>
                <note/>
            </ended>
            <note/>
            <created-by>wicentowskijc</created-by>
            <created-date>2010-05-20</created-date>
            <last-modified-by>wicentowskijc</last-modified-by>
            <last-modified-date>2010-05-20</last-modified-date>
        </principal>
        <principal>
            <id>secr-1987-levi</id>
            <person-id>levitsky-melvyn</person-id>
            <role-title-id>executive-secretary</role-title-id>
            <appointed>
                <date>1987-02-13</date>
                <note/>
            </appointed>
            <started>
                <date/>
                <note/>
            </started>
            <ended>
                <date>1989-03-25</date>
                <note/>
            </ended>
            <note/>
            <created-by>wicentowskijc</created-by>
            <created-date>2010-05-20</created-date>
            <last-modified-by>wicentowskijc</last-modified-by>
            <last-modified-date>2010-05-20</last-modified-date>
        </principal>
        <principal>
            <id>secr-1989-roy</id>
            <person-id>roy-j-stapleton</person-id>
            <role-title-id>executive-secretary</role-title-id>
            <appointed>
                <date>1989-03-26</date>
                <note/>
            </appointed>
            <started>
                <date/>
                <note/>
            </started>
            <ended>
                <date>1991-05-24</date>
                <note/>
            </ended>
            <note/>
            <created-by>wicentowskijc</created-by>
            <created-date>2010-05-20</created-date>
            <last-modified-by>wicentowskijc</last-modified-by>
            <last-modified-date>2013-03-14</last-modified-date>
        </principal>
        <principal>
            <id>secr-1991-pear</id>
            <person-id>pearson-w-robert</person-id>
            <role-title-id>executive-secretary</role-title-id>
            <appointed>
                <date>1991-05-28</date>
                <note/>
            </appointed>
            <started>
                <date/>
                <note/>
            </started>
            <ended>
                <date>1993-01-22</date>
                <note/>
            </ended>
            <note/>
            <created-by>wicentowskijc</created-by>
            <created-date>2010-05-20</created-date>
            <last-modified-by>wicentowskijc</last-modified-by>
            <last-modified-date>2012-09-18</last-modified-date>
        </principal>
        <principal>
            <id>secr-1993-gros</id>
            <person-id>grossman-marc-isaiah</person-id>
            <role-title-id>executive-secretary</role-title-id>
            <appointed>
                <date>1993-01-22</date>
                <note/>
            </appointed>
            <started>
                <date/>
                <note/>
            </started>
            <ended>
                <date>1994-07-29</date>
                <note/>
            </ended>
            <note/>
            <created-by>wicentowskijc</created-by>
            <created-date>2010-05-20</created-date>
            <last-modified-by>wicentowskijc</last-modified-by>
            <last-modified-date>2010-05-20</last-modified-date>
        </principal>
        <principal>
            <id>secr-1994-bril</id>
            <person-id>brill-kenneth-c</person-id>
            <role-title-id>executive-secretary</role-title-id>
            <appointed>
                <date>1994-09-01</date>
                <note/>
            </appointed>
            <started>
                <date/>
                <note/>
            </started>
            <ended>
                <date>1995-12-22</date>
                <note/>
            </ended>
            <note/>
            <created-by>wicentowskijc</created-by>
            <created-date>2010-05-20</created-date>
            <last-modified-by>marrsaw</last-modified-by>
            <last-modified-date>2016-11-14</last-modified-date>
        </principal>
        <principal>
            <id>secr-1996-burn</id>
            <person-id>burns-william-joseph</person-id>
            <role-title-id>executive-secretary</role-title-id>
            <appointed>
                <date>1996-01-16</date>
                <note/>
            </appointed>
            <started>
                <date/>
                <note/>
            </started>
            <ended>
                <date>1998-02-27</date>
                <note/>
            </ended>
            <note/>
            <created-by>wicentowskijc</created-by>
            <created-date>2010-05-20</created-date>
            <last-modified-by>wicentowskijc</last-modified-by>
            <last-modified-date>2012-09-24</last-modified-date>
        </principal>
        <principal>
            <id>secr-1998-kenn</id>
            <person-id>kenney-kristie-ann</person-id>
            <role-title-id>executive-secretary</role-title-id>
            <appointed>
                <date>1998-03-02</date>
                <note/>
            </appointed>
            <started>
                <date/>
                <note/>
            </started>
            <ended>
                <date>2001-04-30</date>
                <note/>
            </ended>
            <note/>
            <created-by>wicentowskijc</created-by>
            <created-date>2010-05-20</created-date>
            <last-modified-by>marrsaw</last-modified-by>
            <last-modified-date>2013-10-01</last-modified-date>
        </principal>
        <principal>
            <id>secr-2001-hart</id>
            <person-id>harty-maura</person-id>
            <role-title-id>executive-secretary</role-title-id>
            <appointed>
                <date>2001-05-01</date>
                <note/>
            </appointed>
            <started>
                <date/>
                <note/>
            </started>
            <ended>
                <date>2002-11-18</date>
                <note/>
            </ended>
            <note/>
            <created-by>wicentowskijc</created-by>
            <created-date>2010-05-20</created-date>
            <last-modified-by>wicentowskijc</last-modified-by>
            <last-modified-date>2010-05-20</last-modified-date>
        </principal>
        <principal>
            <id>secr-2002-hofm</id>
            <person-id>hofmann-karl-william</person-id>
            <role-title-id>executive-secretary</role-title-id>
            <appointed>
                <date>2002-12-19</date>
                <note/>
            </appointed>
            <started>
                <date/>
                <note/>
            </started>
            <ended>
                <date>2005-07-01</date>
                <note/>
            </ended>
            <note/>
            <created-by>wicentowskijc</created-by>
            <created-date>2010-05-20</created-date>
            <last-modified-by>wicentowskijc</last-modified-by>
            <last-modified-date>2010-05-20</last-modified-date>
        </principal>
        <principal>
            <id>secr-2005-thom</id>
            <person-id>thomas-harry-keels</person-id>
            <role-title-id>executive-secretary</role-title-id>
            <appointed>
                <date>2005-07-25</date>
                <note/>
            </appointed>
            <started>
                <date/>
                <note/>
            </started>
            <ended>
                <date>2007-07-27</date>
                <note/>
            </ended>
            <note/>
            <created-by>wicentowskijc</created-by>
            <created-date>2010-05-20</created-date>
            <last-modified-by>marrsaw</last-modified-by>
            <last-modified-date>2014-07-22</last-modified-date>
        </principal>
        <principal>
            <id>secr-2007-smit</id>
            <person-id>smith-daniel-bennett</person-id>
            <role-title-id>executive-secretary</role-title-id>
            <appointed>
                <date/>
                <note/>
            </appointed>
            <started>
                <date>2007-08-06</date>
                <note/>
            </started>
            <ended>
                <date>2009-06-20</date>
                <note/>
            </ended>
            <note/>
            <created-by>wicentowskijc</created-by>
            <created-date>2010-05-20</created-date>
            <last-modified-by>marrsaw</last-modified-by>
            <last-modified-date>2014-07-21</last-modified-date>
        </principal>
        <principal>
            <id>secr-2009-mull</id>
            <person-id>mull-stephen-d</person-id>
            <role-title-id>executive-secretary</role-title-id>
            <appointed>
                <date/>
                <note/>
            </appointed>
            <started>
                <date>2009-06-21</date>
                <note/>
            </started>
            <ended>
                <date>2012-10-05</date>
                <note/>
            </ended>
            <note/>
            <created-by>wicentowskijc</created-by>
            <created-date>2010-05-20</created-date>
            <last-modified-by>marrsaw</last-modified-by>
            <last-modified-date>2013-09-27</last-modified-date>
        </principal>
        <principal>
            <id>secr-2012-bass</id>
            <person-id>bass-john-r</person-id>
            <role-title-id>executive-secretary</role-title-id>
            <appointed>
                <date>2012-10-08</date>
                <note/>
            </appointed>
            <started>
                <date/>
                <note/>
            </started>
            <ended>
                <date>2014-07-18</date>
                <note/>
            </ended>
            <note/>
            <created-by>wicentowskijc</created-by>
            <created-date>2012-04-03</created-date>
            <last-modified-by>marrsaw</last-modified-by>
            <last-modified-date>2015-05-05</last-modified-date>
        </principal>
        <principal>
            <id>secr-2014-macm</id>
            <person-id>macmanus-joseph-e</person-id>
            <role-title-id>executive-secretary</role-title-id>
            <appointed>
                <date>2014-08-04</date>
                <note/>
            </appointed>
            <started>
                <date>2014-08-04</date>
                <note/>
            </started>
            <ended>
                <date>2017-06-15</date>
                <note/>
            </ended>
            <note/>
            <created-by>wicentowskijc</created-by>
            <created-date>2012-04-03</created-date>
            <last-modified-by>marrsaw</last-modified-by>
            <last-modified-date>2017-08-22</last-modified-date>
        </principal>
        <principal>
            <id>secr-2017-kenn</id>
            <person-id>kenna-lisa-d</person-id>
            <role-title-id>executive-secretary</role-title-id>
            <appointed>
                <date/>
                <note/>
            </appointed>
            <started>
                <date>2017-06-15</date>
                <note/>
            </started>
            <ended>
                <date/>
                <note/>
            </ended>
            <note/>
            <created-by>marrsaw</created-by>
            <created-date>2017-08-22</created-date>
            <last-modified-by>bottsjd</last-modified-by>
            <last-modified-date>2019-02-06</last-modified-date>
        </principal>
    </principals>
    <other-appointees/>
</principal-position>