<?xml version="1.0" encoding="UTF-8"?>
<concurrent-appointments>
    <id>2011-wong-01</id>
    <person-id>wong-eric</person-id>
    <resident-at>
        <locale-id>antananarivo</locale-id>
        <contemporary-territory-id>madagascar</contemporary-territory-id>
    </resident-at>
    <chief-id>km-2011-wong-01</chief-id>
    <chief-id>mg-2011-wong-01</chief-id>
    <created-by>marrsaw</created-by>
    <created-date>2015-07-13</created-date>
    <last-modified-by>marrsaw</last-modified-by>
    <last-modified-date>2015-07-13</last-modified-date>
</concurrent-appointments>