<?xml version="1.0" encoding="UTF-8"?>
<concurrent-appointments>
    <id>2019-mcke-01</id>
    <person-id>mckee-erin-e</person-id>
    <resident-at>
        <locale-id>port-moresby</locale-id>
        <contemporary-territory-id>papua-new-guinea</contemporary-territory-id>
    </resident-at>
    <chief-id>pg-2019-mcke-01</chief-id>
    <chief-id>vu-2019-mcke-01</chief-id>
    <chief-id>sb-2019-mcke-01</chief-id>
    <created-by>bottsjd</created-by>
    <created-date>2019-11-13</created-date>
    <last-modified-by>bottsjd</last-modified-by>
    <last-modified-date>2019-11-13</last-modified-date>
</concurrent-appointments>