<?xml version="1.0" encoding="UTF-8"?>
<country-mission>
    <territory-id>luxembourg</territory-id>
    <chiefs>
        <chief>
            <id>lu-1903-newe-01</id>
            <person-id>newel-stanford</person-id>
            <role-title-id>envoy-extraordinary-minister-plenipotentiary</role-title-id>
            <contemporary-territory-id>luxembourg</contemporary-territory-id>
            <appointed>
                <date>1903-06-05</date>
                <note/>
            </appointed>
            <started>
                <date>1903-07-17</date>
                <note/>
            </started>
            <ended>
                <date>1905-06-25</date>
                <note>Presented recall</note>
            </ended>
            <note>Commissioned during a recess of the Senate; recommissioned on November 16, 1903,
                after confirmation.</note>
            <created-by>wicentowskijc</created-by>
            <created-date>2010-05-20</created-date>
            <last-modified-by>marrsaw</last-modified-by>
            <last-modified-date>2016-01-05</last-modified-date>
        </chief>
        <chief>
            <id>lu-1905-hill-01</id>
            <person-id>hill-david-jayne</person-id>
            <role-title-id>envoy-extraordinary-minister-plenipotentiary</role-title-id>
            <contemporary-territory-id>luxembourg</contemporary-territory-id>
            <appointed>
                <date>1905-03-15</date>
                <note/>
            </appointed>
            <started>
                <date>1905-08-17</date>
                <note/>
            </started>
            <ended>
                <date>1908-06-10</date>
                <note>Presented recall</note>
            </ended>
            <note>Accredited also to the Netherlands; resident at The Hague.</note>
            <created-by>wicentowskijc</created-by>
            <created-date>2010-05-20</created-date>
            <last-modified-by>wicentowskijc</last-modified-by>
            <last-modified-date>2010-05-20</last-modified-date>
        </chief>
        <chief>
            <id>lu-1908-beau-01</id>
            <person-id>beaupre-arthur-matthias</person-id>
            <role-title-id>envoy-extraordinary-minister-plenipotentiary</role-title-id>
            <contemporary-territory-id>luxembourg</contemporary-territory-id>
            <appointed>
                <date>1908-04-02</date>
                <note/>
            </appointed>
            <started>
                <date>1908-07-08</date>
                <note/>
            </started>
            <ended>
                <date>1911-09-25</date>
                <note>Relinquished charge at The Hague</note>
            </ended>
            <note/>
            <created-by>wicentowskijc</created-by>
            <created-date>2010-05-20</created-date>
            <last-modified-by>marrsaw</last-modified-by>
            <last-modified-date>2016-01-05</last-modified-date>
        </chief>
        <chief>
            <id>lu-1911-bryc-01</id>
            <person-id>bryce-lloyd-stephens</person-id>
            <role-title-id>envoy-extraordinary-minister-plenipotentiary</role-title-id>
            <contemporary-territory-id>luxembourg</contemporary-territory-id>
            <appointed>
                <date>1911-08-12</date>
                <note/>
            </appointed>
            <started>
                <date>1911-12-07</date>
                <note/>
            </started>
            <ended>
                <date>1913-09-10</date>
                <note>Relinquished charge at The Hague</note>
            </ended>
            <note/>
            <created-by>wicentowskijc</created-by>
            <created-date>2010-05-20</created-date>
            <last-modified-by>marrsaw</last-modified-by>
            <last-modified-date>2016-01-05</last-modified-date>
        </chief>
        <chief>
            <id>lu-1913-van-01</id>
            <person-id>van-dyke-henry</person-id>
            <role-title-id>envoy-extraordinary-minister-plenipotentiary</role-title-id>
            <contemporary-territory-id>luxembourg</contemporary-territory-id>
            <appointed>
                <date>1913-06-27</date>
                <note/>
            </appointed>
            <started>
                <date>1913-11-20</date>
                <note/>
            </started>
            <ended>
                <date>1917-01-15</date>
                <note>Left The Hague</note>
            </ended>
            <note/>
            <created-by>wicentowskijc</created-by>
            <created-date>2010-05-20</created-date>
            <last-modified-by>marrsaw</last-modified-by>
            <last-modified-date>2016-01-05</last-modified-date>
        </chief>
        <chief>
            <id>lu-1917-garr-01</id>
            <person-id>garrett-john-work</person-id>
            <role-title-id>envoy-extraordinary-minister-plenipotentiary</role-title-id>
            <contemporary-territory-id>luxembourg</contemporary-territory-id>
            <appointed>
                <date>1917-08-23</date>
                <note/>
            </appointed>
            <started subtype="bracketed">
                <date>1917-11-11</date>
                <note>Transmitted credentials by note on</note>
            </started>
            <ended>
                <date>1919-06-18</date>
                <note>Left The Hague</note>
            </ended>
            <note/>
            <created-by>wicentowskijc</created-by>
            <created-date>2010-05-20</created-date>
            <last-modified-by>marrsaw</last-modified-by>
            <last-modified-date>2016-01-05</last-modified-date>
        </chief>
        <chief>
            <id>lu-1920-phil-01</id>
            <person-id>phillips-william</person-id>
            <role-title-id>envoy-extraordinary-minister-plenipotentiary</role-title-id>
            <contemporary-territory-id>luxembourg</contemporary-territory-id>
            <appointed>
                <date>1920-03-03</date>
                <note/>
            </appointed>
            <started>
                <date>1920-05-18</date>
                <note/>
            </started>
            <ended>
                <date>1922-04-11</date>
                <note>Left The Hague</note>
            </ended>
            <note/>
            <created-by>wicentowskijc</created-by>
            <created-date>2010-05-20</created-date>
            <last-modified-by>marrsaw</last-modified-by>
            <last-modified-date>2016-01-05</last-modified-date>
        </chief>
        <chief>
            <id>lu-1923-flet-01</id>
            <person-id>fletcher-henry-prather</person-id>
            <role-title-id>envoy-extraordinary-minister-plenipotentiary</role-title-id>
            <contemporary-territory-id>luxembourg</contemporary-territory-id>
            <appointed>
                <date>1923-03-05</date>
                <note/>
            </appointed>
            <started>
                <date>1923-10-29</date>
                <note/>
            </started>
            <ended>
                <date>1924-03-25</date>
                <note>Left Brussels</note>
            </ended>
            <note>Commissioned during a recess of the Senate; recommissioned on December 12, 1923,
                after confirmation.</note>
            <created-by>wicentowskijc</created-by>
            <created-date>2010-05-20</created-date>
            <last-modified-by>marrsaw</last-modified-by>
            <last-modified-date>2016-01-05</last-modified-date>
        </chief>
        <chief>
            <id>lu-1924-phil-01</id>
            <person-id>phillips-william</person-id>
            <role-title-id>envoy-extraordinary-minister-plenipotentiary</role-title-id>
            <contemporary-territory-id>luxembourg</contemporary-territory-id>
            <appointed>
                <date>1924-02-29</date>
                <note/>
            </appointed>
            <started>
                <date>1924-07-12</date>
                <note/>
            </started>
            <ended>
                <date>1927-03-01</date>
                <note>Left Brussels</note>
            </ended>
            <note/>
            <created-by>wicentowskijc</created-by>
            <created-date>2010-05-20</created-date>
            <last-modified-by>marrsaw</last-modified-by>
            <last-modified-date>2016-01-05</last-modified-date>
        </chief>
        <chief>
            <id>lu-1927-gibs-01</id>
            <person-id>gibson-hugh-simons</person-id>
            <role-title-id>envoy-extraordinary-minister-plenipotentiary</role-title-id>
            <contemporary-territory-id>luxembourg</contemporary-territory-id>
            <appointed>
                <date>1927-02-17</date>
                <note/>
            </appointed>
            <started>
                <date>1927-12-19</date>
                <note/>
            </started>
            <ended>
                <date>1933-06-11</date>
                <note>Left Brussels</note>
            </ended>
            <note>On October 8, 1931, during Gibson's tenure as non-resident Minister, Gibson
                introduced George P. Waller to the Minister of State in Luxembourg, in Waller's
                capacity as Second Secretary of Legation and Consul. Gibson then returned to
                Brussels on October 9, 1931, leaving Waller in charge at Luxembourg, the Department
                of State having previously authorized the Consul and Second Secretary at that post
                to act as Charge d'Affaires ad interim in the absence of the Minister and First
                Secretary.</note>
            <created-by>wicentowskijc</created-by>
            <created-date>2010-05-20</created-date>
            <last-modified-by>marrsaw</last-modified-by>
            <last-modified-date>2016-01-05</last-modified-date>
        </chief>
        <chief>
            <id>lu-1933-morr-01</id>
            <person-id>morris-dave-hennen</person-id>
            <role-title-id>envoy-extraordinary-minister-plenipotentiary</role-title-id>
            <contemporary-territory-id>luxembourg</contemporary-territory-id>
            <appointed>
                <date>1933-05-18</date>
                <note/>
            </appointed>
            <started>
                <date>1933-11-04</date>
                <note/>
            </started>
            <ended>
                <date>1937-05-05</date>
                <note>Left Brussels</note>
            </ended>
            <note/>
            <created-by>wicentowskijc</created-by>
            <created-date>2010-05-20</created-date>
            <last-modified-by>marrsaw</last-modified-by>
            <last-modified-date>2016-01-05</last-modified-date>
        </chief>
        <chief>
            <id>lu-1937-gibs-01</id>
            <person-id>gibson-hugh-simons</person-id>
            <role-title-id>envoy-extraordinary-minister-plenipotentiary</role-title-id>
            <contemporary-territory-id>luxembourg</contemporary-territory-id>
            <appointed>
                <date>1937-07-13</date>
                <note/>
            </appointed>
            <started>
                <date>1937-11-15</date>
                <note/>
            </started>
            <ended>
                <date>1938-06-15</date>
                <note>Left Brussels</note>
            </ended>
            <note/>
            <created-by>wicentowskijc</created-by>
            <created-date>2010-05-20</created-date>
            <last-modified-by>marrsaw</last-modified-by>
            <last-modified-date>2016-01-05</last-modified-date>
        </chief>
        <chief>
            <id>lu-1938-davi-01</id>
            <person-id>davies-joseph-edward</person-id>
            <role-title-id>envoy-extraordinary-minister-plenipotentiary</role-title-id>
            <contemporary-territory-id>luxembourg</contemporary-territory-id>
            <appointed>
                <date>1938-05-14</date>
                <note/>
            </appointed>
            <started>
                <date>1938-07-26</date>
                <note/>
            </started>
            <ended>
                <date>1939-11-30</date>
                <note>Left Brussels</note>
            </ended>
            <note/>
            <created-by>wicentowskijc</created-by>
            <created-date>2010-05-20</created-date>
            <last-modified-by>marrsaw</last-modified-by>
            <last-modified-date>2016-01-05</last-modified-date>
        </chief>
        <chief>
            <id>lu-1940-cuda-01</id>
            <person-id>cudahy-john-clarence</person-id>
            <role-title-id>envoy-extraordinary-minister-plenipotentiary</role-title-id>
            <contemporary-territory-id>luxembourg</contemporary-territory-id>
            <appointed>
                <date>1940-01-12</date>
                <note/>
            </appointed>
            <started>
                <date>1940-02-12</date>
                <note/>
            </started>
            <ended>
                <date>1940-05-10</date>
                <note>German forces occupied Luxembourg on</note>
            </ended>
            <note>Cudahy left Brussels on July 18, 1940. George P. Waller was serving as Chargé
                d’Affaires ad interim when Legation Luxembourg was closed on July 15, 1940.</note>
            <created-by>wicentowskijc</created-by>
            <created-date>2010-05-20</created-date>
            <last-modified-by>wicentowskijc</last-modified-by>
            <last-modified-date>2010-05-20</last-modified-date>
        </chief>
        <chief>
            <id>lu-1941-moff-01</id>
            <person-id>moffat-jay-pierrepont</person-id>
            <role-title-id>envoy-extraordinary-minister-plenipotentiary</role-title-id>
            <contemporary-territory-id>luxembourg</contemporary-territory-id>
            <appointed>
                <date>1941-02-11</date>
                <note/>
            </appointed>
            <started>
                <date>1941-03-10</date>
                <note/>
            </started>
            <ended>
                <date>1943-01-24</date>
                <note>Died at Ottawa</note>
            </ended>
            <note/>
            <created-by>wicentowskijc</created-by>
            <created-date>2010-05-20</created-date>
            <last-modified-by>marrsaw</last-modified-by>
            <last-modified-date>2016-01-05</last-modified-date>
        </chief>
        <chief>
            <id>lu-1943-athe-01</id>
            <person-id>atherton-ray</person-id>
            <role-title-id>envoy-extraordinary-minister-plenipotentiary</role-title-id>
            <contemporary-territory-id>luxembourg</contemporary-territory-id>
            <appointed>
                <date>1943-07-08</date>
                <note/>
            </appointed>
            <started>
                <date>1943-09-10</date>
                <note/>
            </started>
            <ended>
                <date>1943-10-14</date>
                <note>Government of Luxembourg transferred to England</note>
            </ended>
            <note/>
            <created-by>wicentowskijc</created-by>
            <created-date>2010-05-20</created-date>
            <last-modified-by>marrsaw</last-modified-by>
            <last-modified-date>2016-01-05</last-modified-date>
        </chief>
        <chief>
            <id>lu-1944-scho-01</id>
            <person-id>schoenfeld-rudolf-emil</person-id>
            <role-title-id>charge-daffaires</role-title-id>
            <contemporary-territory-id>luxembourg</contemporary-territory-id>
            <appointed>
                <date>1944-03-21</date>
                <note/>
            </appointed>
            <started subtype="see-note">
                <date/>
                <note>No record has been found of the issuance or presentation of a letter of
                    credence.</note>
            </started>
            <ended>
                <date>1944-11-01</date>
                <note>Superseded</note>
            </ended>
            <note>Served near the Government of Luxembourg established in the United Kingdom;
                resident at London.</note>
            <created-by>wicentowskijc</created-by>
            <created-date>2010-05-20</created-date>
            <last-modified-by>marrsaw</last-modified-by>
            <last-modified-date>2016-01-05</last-modified-date>
        </chief>
        <chief>
            <id>lu-1944-gree-01</id>
            <person-id>greene-winthrop-stephenson</person-id>
            <role-title-id>charge-daffaires-ad-interim</role-title-id>
            <contemporary-territory-id>luxembourg</contemporary-territory-id>
            <appointed>
                <date/>
                <note/>
            </appointed>
            <started>
                <date>1944-09-23</date>
                <note>Legation Luxembourg reestablished on</note>
            </started>
            <ended>
                <date/>
                <note/>
            </ended>
            <note/>
            <created-by>wicentowskijc</created-by>
            <created-date>2010-05-20</created-date>
            <last-modified-by>marrsaw</last-modified-by>
            <last-modified-date>2016-01-05</last-modified-date>
        </chief>
        <chief>
            <id>lu-1944-sawy-01</id>
            <person-id>sawyer-charles</person-id>
            <role-title-id>envoy-extraordinary-minister-plenipotentiary</role-title-id>
            <contemporary-territory-id>luxembourg</contemporary-territory-id>
            <appointed>
                <date>1944-09-21</date>
                <note/>
            </appointed>
            <started>
                <date>1944-11-01</date>
                <note/>
            </started>
            <ended>
                <date>1945-11-20</date>
                <note>Left Brussels</note>
            </ended>
            <note/>
            <created-by>wicentowskijc</created-by>
            <created-date>2010-05-20</created-date>
            <last-modified-by>marrsaw</last-modified-by>
            <last-modified-date>2016-01-06</last-modified-date>
        </chief>
        <chief>
            <id>lu-1946-kirk-01</id>
            <person-id>kirk-alan-goodrich</person-id>
            <role-title-id>envoy-extraordinary-minister-plenipotentiary</role-title-id>
            <contemporary-territory-id>luxembourg</contemporary-territory-id>
            <appointed>
                <date>1946-02-01</date>
                <note/>
            </appointed>
            <started>
                <date>1946-04-24</date>
                <note/>
            </started>
            <ended>
                <date>1949-05-06</date>
                <note>Left Brussels</note>
            </ended>
            <note/>
            <created-by>wicentowskijc</created-by>
            <created-date>2010-05-20</created-date>
            <last-modified-by>marrsaw</last-modified-by>
            <last-modified-date>2016-01-05</last-modified-date>
        </chief>
        <chief>
            <id>lu-1949-mest-01</id>
            <person-id>mesta-perle-pearl-reid-skirvin</person-id>
            <role-title-id>envoy-extraordinary-minister-plenipotentiary</role-title-id>
            <contemporary-territory-id>luxembourg</contemporary-territory-id>
            <appointed>
                <date>1949-07-06</date>
                <note/>
            </appointed>
            <started>
                <date>1949-09-21</date>
                <note/>
            </started>
            <ended>
                <date>1953-04-13</date>
                <note>Left post.</note>
            </ended>
            <note>The status of the post at Luxembourg as a resident Legation was confirmed by an
                instruction dated June 14, 1952.</note>
            <created-by>wicentowskijc</created-by>
            <created-date>2010-05-20</created-date>
            <last-modified-by>marrsaw</last-modified-by>
            <last-modified-date>2016-01-05</last-modified-date>
        </chief>
        <chief>
            <id>lu-1953-buch-01</id>
            <person-id>buchanan-wiley-thomas</person-id>
            <role-title-id>envoy-extraordinary-minister-plenipotentiary</role-title-id>
            <contemporary-territory-id>luxembourg</contemporary-territory-id>
            <appointed>
                <date>1953-09-12</date>
                <note/>
            </appointed>
            <started>
                <date>1953-12-01</date>
                <note/>
            </started>
            <ended>
                <date>1956-09-21</date>
                <note>Promoted to Ambassador Extraordinary and Plenipotentiary</note>
            </ended>
            <note>Commissioned during a recess of the Senate; recommissioned on January 26, 1954,
                after confirmation.</note>
            <created-by>wicentowskijc</created-by>
            <created-date>2010-05-20</created-date>
            <last-modified-by>marrsaw</last-modified-by>
            <last-modified-date>2016-01-05</last-modified-date>
        </chief>
        <chief>
            <id>lu-1956-buch-01</id>
            <person-id>buchanan-wiley-thomas</person-id>
            <role-title-id>ambassador-e-p</role-title-id>
            <contemporary-territory-id>luxembourg</contemporary-territory-id>
            <appointed>
                <date>1956-09-09</date>
                <note/>
            </appointed>
            <started>
                <date>1956-09-21</date>
                <note/>
            </started>
            <ended>
                <date>1956-12-20</date>
                <note>Left post.</note>
            </ended>
            <note>Commissioned during a recess of the Senate; recommissioned on January 25, 1956,
                after confirmation.</note>
            <created-by>wicentowskijc</created-by>
            <created-date>2010-05-20</created-date>
            <last-modified-by>marrsaw</last-modified-by>
            <last-modified-date>2016-01-05</last-modified-date>
        </chief>
        <chief>
            <id>lu-1957-chap-01</id>
            <person-id>chapin-vinton</person-id>
            <role-title-id>ambassador-e-p</role-title-id>
            <contemporary-territory-id>luxembourg</contemporary-territory-id>
            <appointed>
                <date>1957-07-03</date>
                <note/>
            </appointed>
            <started>
                <date>1957-10-29</date>
                <note/>
            </started>
            <ended>
                <date>1960-07-31</date>
                <note>Left post.</note>
            </ended>
            <note/>
            <created-by>wicentowskijc</created-by>
            <created-date>2010-05-20</created-date>
            <last-modified-by>wicentowskijc</last-modified-by>
            <last-modified-date>2010-05-20</last-modified-date>
        </chief>
        <chief>
            <id>lu-1960-summ-01</id>
            <person-id>summers-allingham-burks</person-id>
            <role-title-id>ambassador-e-p</role-title-id>
            <contemporary-territory-id>luxembourg</contemporary-territory-id>
            <appointed>
                <date>1960-06-24</date>
                <note/>
            </appointed>
            <started>
                <date>1960-09-16</date>
                <note/>
            </started>
            <ended>
                <date>1961-04-01</date>
                <note>Left post.</note>
            </ended>
            <note/>
            <created-by>wicentowskijc</created-by>
            <created-date>2010-05-20</created-date>
            <last-modified-by>wicentowskijc</last-modified-by>
            <last-modified-date>2010-05-20</last-modified-date>
        </chief>
        <chief>
            <id>lu-1961-wine-01</id>
            <person-id>wine-james-wilmer</person-id>
            <role-title-id>ambassador-e-p</role-title-id>
            <contemporary-territory-id>luxembourg</contemporary-territory-id>
            <appointed>
                <date>1961-04-27</date>
                <note/>
            </appointed>
            <started>
                <date>1961-05-26</date>
                <note/>
            </started>
            <ended>
                <date>1962-10-24</date>
                <note>Left post.</note>
            </ended>
            <note/>
            <created-by>wicentowskijc</created-by>
            <created-date>2010-05-20</created-date>
            <last-modified-by>wicentowskijc</last-modified-by>
            <last-modified-date>2012-03-05</last-modified-date>
        </chief>
        <chief>
            <id>lu-1962-rivk-01</id>
            <person-id>rivkin-william-robert</person-id>
            <role-title-id>ambassador-e-p</role-title-id>
            <contemporary-territory-id>luxembourg</contemporary-territory-id>
            <appointed>
                <date>1962-11-05</date>
                <note/>
            </appointed>
            <started>
                <date>1962-12-18</date>
                <note/>
            </started>
            <ended>
                <date>1965-06-07</date>
                <note>Left post.</note>
            </ended>
            <note>Commissioned during a recess of the Senate; recommissioned on March 12, 1963,
                after confirmation.</note>
            <created-by>wicentowskijc</created-by>
            <created-date>2010-05-20</created-date>
            <last-modified-by>marrsaw</last-modified-by>
            <last-modified-date>2016-01-05</last-modified-date>
        </chief>
        <chief>
            <id>lu-1965-harr-01</id>
            <person-id>harris-patricia-roberts</person-id>
            <role-title-id>ambassador-e-p</role-title-id>
            <contemporary-territory-id>luxembourg</contemporary-territory-id>
            <appointed>
                <date>1965-06-04</date>
                <note/>
            </appointed>
            <started>
                <date>1965-09-07</date>
                <note/>
            </started>
            <ended>
                <date>1967-09-22</date>
                <note>Left post.</note>
            </ended>
            <note/>
            <created-by>wicentowskijc</created-by>
            <created-date>2010-05-20</created-date>
            <last-modified-by>wicentowskijc</last-modified-by>
            <last-modified-date>2010-05-20</last-modified-date>
        </chief>
        <chief>
            <id>lu-1967-feld-01</id>
            <person-id>feldman-george-joseph</person-id>
            <role-title-id>ambassador-e-p</role-title-id>
            <contemporary-territory-id>luxembourg</contemporary-territory-id>
            <appointed>
                <date>1967-10-18</date>
                <note/>
            </appointed>
            <started>
                <date>1967-12-20</date>
                <note/>
            </started>
            <ended>
                <date>1969-07-07</date>
                <note>Left post.</note>
            </ended>
            <note/>
            <created-by>wicentowskijc</created-by>
            <created-date>2010-05-20</created-date>
            <last-modified-by>wicentowskijc</last-modified-by>
            <last-modified-date>2010-05-20</last-modified-date>
        </chief>
        <chief>
            <id>lu-1969-goul-01</id>
            <person-id>gould-kingdon-jr</person-id>
            <role-title-id>ambassador-e-p</role-title-id>
            <contemporary-territory-id>luxembourg</contemporary-territory-id>
            <appointed>
                <date>1969-05-27</date>
                <note/>
            </appointed>
            <started>
                <date>1969-07-11</date>
                <note/>
            </started>
            <ended>
                <date>1972-10-02</date>
                <note>Left post.</note>
            </ended>
            <note/>
            <created-by>wicentowskijc</created-by>
            <created-date>2010-05-20</created-date>
            <last-modified-by>wicentowskijc</last-modified-by>
            <last-modified-date>2010-05-20</last-modified-date>
        </chief>
        <chief>
            <id>lu-1973-fark-01</id>
            <person-id>farkas-ruby-ruth-lewis</person-id>
            <role-title-id>ambassador-e-p</role-title-id>
            <contemporary-territory-id>luxembourg</contemporary-territory-id>
            <appointed>
                <date>1973-03-27</date>
                <note/>
            </appointed>
            <started>
                <date>1973-05-11</date>
                <note/>
            </started>
            <ended>
                <date>1976-03-18</date>
                <note>Left post.</note>
            </ended>
            <note/>
            <created-by>wicentowskijc</created-by>
            <created-date>2010-05-20</created-date>
            <last-modified-by>wicentowskijc</last-modified-by>
            <last-modified-date>2010-05-20</last-modified-date>
        </chief>
        <chief>
            <id>lu-1976-ginn-01</id>
            <person-id>ginn-rosemary-lucas</person-id>
            <role-title-id>ambassador-e-p</role-title-id>
            <contemporary-territory-id>luxembourg</contemporary-territory-id>
            <appointed>
                <date>1976-05-21</date>
                <note/>
            </appointed>
            <started>
                <date>1976-06-08</date>
                <note/>
            </started>
            <ended>
                <date>1977-05-23</date>
                <note>Left post.</note>
            </ended>
            <note/>
            <created-by>wicentowskijc</created-by>
            <created-date>2010-05-20</created-date>
            <last-modified-by>marrsaw</last-modified-by>
            <last-modified-date>2013-04-09</last-modified-date>
        </chief>
        <chief>
            <id>lu-1977-lowe-01</id>
            <person-id>lowenstein-james-gordon</person-id>
            <role-title-id>ambassador-e-p</role-title-id>
            <contemporary-territory-id>luxembourg</contemporary-territory-id>
            <appointed>
                <date>1977-05-26</date>
                <note/>
            </appointed>
            <started>
                <date>1977-06-21</date>
                <note/>
            </started>
            <ended>
                <date>1981-07-22</date>
                <note>Left post.</note>
            </ended>
            <note/>
            <created-by>wicentowskijc</created-by>
            <created-date>2010-05-20</created-date>
            <last-modified-by>wicentowskijc</last-modified-by>
            <last-modified-date>2010-05-20</last-modified-date>
        </chief>
        <chief>
            <id>lu-1981-doli-01</id>
            <person-id>dolibois-john-ernest</person-id>
            <role-title-id>ambassador-e-p</role-title-id>
            <contemporary-territory-id>luxembourg</contemporary-territory-id>
            <appointed>
                <date>1981-09-28</date>
                <note/>
            </appointed>
            <started>
                <date>1981-10-12</date>
                <note/>
            </started>
            <ended>
                <date>1985-09-17</date>
                <note>Left post.</note>
            </ended>
            <note/>
            <created-by>wicentowskijc</created-by>
            <created-date>2010-05-20</created-date>
            <last-modified-by>marrsaw</last-modified-by>
            <last-modified-date>2014-09-08</last-modified-date>
        </chief>
        <chief>
            <id>lu-1985-gera-01</id>
            <person-id>gerard-jean-broward-shevlin</person-id>
            <role-title-id>ambassador-e-p</role-title-id>
            <contemporary-territory-id>luxembourg</contemporary-territory-id>
            <appointed>
                <date>1985-10-17</date>
                <note/>
            </appointed>
            <started>
                <date>1985-10-30</date>
                <note/>
            </started>
            <ended>
                <date>1990-03-27</date>
                <note>Left post.</note>
            </ended>
            <note/>
            <created-by>wicentowskijc</created-by>
            <created-date>2010-05-20</created-date>
            <last-modified-by>marrsaw</last-modified-by>
            <last-modified-date>2014-01-13</last-modified-date>
        </chief>
        <chief>
            <id>lu-1990-rowe-01</id>
            <person-id>rowell-edward-morgan</person-id>
            <role-title-id>ambassador-e-p</role-title-id>
            <contemporary-territory-id>luxembourg</contemporary-territory-id>
            <appointed>
                <date>1990-04-01</date>
                <note/>
            </appointed>
            <started>
                <date>1990-05-10</date>
                <note/>
            </started>
            <ended>
                <date>1994-08-03</date>
                <note>Left post.</note>
            </ended>
            <note/>
            <created-by>wicentowskijc</created-by>
            <created-date>2010-05-20</created-date>
            <last-modified-by>wicentowskijc</last-modified-by>
            <last-modified-date>2010-05-20</last-modified-date>
        </chief>
        <chief>
            <id>lu-1994-cons-01</id>
            <person-id>constantinou-clay</person-id>
            <role-title-id>ambassador-e-p</role-title-id>
            <contemporary-territory-id>luxembourg</contemporary-territory-id>
            <appointed>
                <date>1994-07-07</date>
                <note/>
            </appointed>
            <started>
                <date>1994-09-07</date>
                <note/>
            </started>
            <ended>
                <date>1999-01-30</date>
                <note>Left post.</note>
            </ended>
            <note/>
            <created-by>wicentowskijc</created-by>
            <created-date>2010-05-20</created-date>
            <last-modified-by>wicentowskijc</last-modified-by>
            <last-modified-date>2010-05-20</last-modified-date>
        </chief>
        <chief>
            <id>lu-1999-horm-01</id>
            <person-id>hormel-james-catherwood</person-id>
            <role-title-id>ambassador-e-p</role-title-id>
            <contemporary-territory-id>luxembourg</contemporary-territory-id>
            <appointed>
                <date>1999-06-10</date>
                <note/>
            </appointed>
            <started>
                <date>1999-09-08</date>
                <note/>
            </started>
            <ended>
                <date>2001-01-01</date>
                <note>Left post.</note>
            </ended>
            <note>Commissioned during a recess of the Senate.</note>
            <created-by>wicentowskijc</created-by>
            <created-date>2010-05-20</created-date>
            <last-modified-by>marrsaw</last-modified-by>
            <last-modified-date>2016-01-05</last-modified-date>
        </chief>
        <chief>
            <id>lu-2001-loft-01</id>
            <person-id>loftus-gerald-j</person-id>
            <role-title-id>charge-daffaires-ad-interim</role-title-id>
            <contemporary-territory-id>luxembourg</contemporary-territory-id>
            <appointed>
                <date/>
                <note/>
            </appointed>
            <started>
                <date>2001-01</date>
                <note/>
            </started>
            <ended>
                <date>2002-04</date>
                <note/>
            </ended>
            <note/>
            <created-by>marrsaw</created-by>
            <created-date>2016-01-04</created-date>
            <last-modified-by>marrsaw</last-modified-by>
            <last-modified-date>2016-01-04</last-modified-date>
        </chief>
        <chief>
            <id>lu-2002-terp-01</id>
            <person-id>terpeluk-peter</person-id>
            <role-title-id>ambassador-e-p</role-title-id>
            <contemporary-territory-id>luxembourg</contemporary-territory-id>
            <appointed>
                <date>2002-04-01</date>
                <note/>
            </appointed>
            <started>
                <date>2002-04-30</date>
                <note/>
            </started>
            <ended>
                <date>2005-07-11</date>
                <note/>
            </ended>
            <note/>
            <created-by>wicentowskijc</created-by>
            <created-date>2010-05-20</created-date>
            <last-modified-by>wicentowskijc</last-modified-by>
            <last-modified-date>2012-09-24</last-modified-date>
        </chief>
        <chief>
            <id>lu-2005-wagn-01</id>
            <person-id>wagner-anne-louise</person-id>
            <role-title-id>ambassador-e-p</role-title-id>
            <contemporary-territory-id>luxembourg</contemporary-territory-id>
            <appointed>
                <date>2005-06-21</date>
                <note/>
            </appointed>
            <started>
                <date>2005-08-16</date>
                <note/>
            </started>
            <ended>
                <date>2009-06-27</date>
                <note>Left post.</note>
            </ended>
            <note/>
            <created-by>wicentowskijc</created-by>
            <created-date>2010-05-20</created-date>
            <last-modified-by>marrsaw</last-modified-by>
            <last-modified-date>2015-08-10</last-modified-date>
        </chief>
        <chief>
            <id>lu-2009-stro-01</id>
            <person-id>stroum-cynthia</person-id>
            <role-title-id>ambassador-e-p</role-title-id>
            <contemporary-territory-id>luxembourg</contemporary-territory-id>
            <appointed>
                <date>2009-11-23</date>
                <note/>
            </appointed>
            <started>
                <date>2010-01-28</date>
                <note/>
            </started>
            <ended>
                <date>2011-01-31</date>
                <note>Left post.</note>
            </ended>
            <note/>
            <created-by>wicentowskijc</created-by>
            <created-date>2012-04-03</created-date>
            <last-modified-by>wicentowskijc</last-modified-by>
            <last-modified-date>2012-09-24</last-modified-date>
        </chief>
        <chief>
            <id>lu-2011-mand-01</id>
            <person-id>mandell-robert-a</person-id>
            <role-title-id>ambassador-e-p</role-title-id>
            <contemporary-territory-id>luxembourg</contemporary-territory-id>
            <appointed>
                <date>2011-10-19</date>
                <note/>
            </appointed>
            <started>
                <date>2011-11-16</date>
                <note/>
            </started>
            <ended>
                <date>2015-02-26</date>
                <note>Left post.</note>
            </ended>
            <note/>
            <created-by>wicentowskijc</created-by>
            <created-date>2012-09-24</created-date>
            <last-modified-by>marrsaw</last-modified-by>
            <last-modified-date>2016-08-24</last-modified-date>
        </chief>
        <chief>
            <id>lu-2016-mcke-01</id>
            <person-id>mckean-david</person-id>
            <role-title-id>ambassador-e-p</role-title-id>
            <contemporary-territory-id>luxembourg</contemporary-territory-id>
            <appointed>
                <date>2016-03-03</date>
                <note/>
            </appointed>
            <started>
                <date/>
                <note/>
            </started>
            <ended>
                <date/>
                <note/>
            </ended>
            <note/>
            <created-by>marrsaw</created-by>
            <created-date>2016-08-24</created-date>
            <last-modified-by>marrsaw</last-modified-by>
            <last-modified-date>2016-08-24</last-modified-date>
        </chief>
    </chiefs>
    <other-nominees>
        <chief>
            <id>lu-1923-tobi-01</id>
            <person-id>tobin-richard-montgomery</person-id>
            <role-title-id>envoy-extraordinary-minister-plenipotentiary</role-title-id>
            <contemporary-territory-id>luxembourg</contemporary-territory-id>
            <appointed>
                <date>1923-02-27</date>
                <note/>
            </appointed>
            <started>
                <date/>
                <note/>
            </started>
            <ended>
                <date/>
                <note/>
            </ended>
            <note>Did not serve under this appointment.</note>
            <created-by>wicentowskijc</created-by>
            <created-date>2010-05-20</created-date>
            <last-modified-by>marrsaw</last-modified-by>
            <last-modified-date>2016-01-05</last-modified-date>
        </chief>
        <chief>
            <id>lu-1943-bidd-01</id>
            <person-id>biddle-anthony-joseph-drexel-jr</person-id>
            <role-title-id>envoy-extraordinary-minister-plenipotentiary</role-title-id>
            <contemporary-territory-id>luxembourg</contemporary-territory-id>
            <appointed>
                <date>1943-11-12</date>
                <note/>
            </appointed>
            <started>
                <date/>
                <note/>
            </started>
            <ended>
                <date/>
                <note/>
            </ended>
            <note>Took oath of office as Envoy Extraordinary and Minister Plenipotentiary to
                Luxembourg after he left London and did not return to post.</note>
            <created-by>wicentowskijc</created-by>
            <created-date>2010-05-20</created-date>
            <last-modified-by>marrsaw</last-modified-by>
            <last-modified-date>2016-01-04</last-modified-date>
        </chief>
        <chief>
            <id>lu--bush-01</id>
            <person-id>bush-frederick-morris</person-id>
            <role-title-id>ambassador-e-p</role-title-id>
            <contemporary-territory-id>luxembourg</contemporary-territory-id>
            <appointed>
                <date/>
                <note/>
            </appointed>
            <started>
                <date/>
                <note/>
            </started>
            <ended>
                <date/>
                <note/>
            </ended>
            <note>Nomination returned after the August 1989 recess and not resubmitted.</note>
            <created-by>wicentowskijc</created-by>
            <created-date>2010-05-20</created-date>
            <last-modified-by>marrsaw</last-modified-by>
            <last-modified-date>2016-01-05</last-modified-date>
        </chief>
    </other-nominees>
    <created-by>wicentowskijc</created-by>
    <created-date>2014-09-17</created-date>
    <last-modified-by>wicentowskijc</last-modified-by>
    <last-modified-date>2014-09-17</last-modified-date>
</country-mission>
