<?xml version="1.0" encoding="UTF-8"?>
<person>
    <id>messersmith-george-strausser</id>
    <persName>
        <surname>Messersmith</surname>
        <forename>George Strausser</forename>
        <altname>George S. Messersmith</altname>
    </persName>
    <birth>1883</birth>
    <death>1960</death>
    <career-type>career</career-type>
    <residence>
        <state-id>de</state-id>
    </residence>
    <created-by>wicentowskijc</created-by>
    <created-date>2010-05-20</created-date>
    <last-modified-by>wicentowskijc</last-modified-by>
    <last-modified-date>2010-05-20</last-modified-date>
</person>